cobra/__init__.py
cobra/cluster.py
cobra/network.py
cobra_brain-1.0.4.dist-info/licenses/LICENSE
cobra_brain-1.0.4.dist-info/METADATA
cobra_brain-1.0.4.dist-info/WHEEL
cobra_brain-1.0.4.dist-info/top_level.txt
cobra_brain-1.0.4.dist-info/RECORD
