Metadata-Version: 2.4
Name: cobra-brain
Version: 1.0.4
Summary: A Python library for brain connectivity analysis and visualization
Home-page: https://github.com/siddlokray/cobra
Author: Sidd Lokray
Author-email: Sidd Lokray <siddharthlokray@gmail.com>
License: MIT
Project-URL: Homepage, https://github.com/siddlokray/cobra
Project-URL: Documentation, https://cobra.readthedocs.io/
Project-URL: Repository, https://github.com/siddlokray/cobra.git
Project-URL: Bug Tracker, https://github.com/siddlokray/cobra/issues
Keywords: neuroscience,connectivity,brain,network,clustering,visualization
Classifier: Development Status :: 3 - Alpha
Classifier: Intended Audience :: Science/Research
Classifier: Topic :: Scientific/Engineering :: Medical Science Apps.
Classifier: Topic :: Scientific/Engineering :: Visualization
Classifier: License :: OSI Approved :: MIT License
Classifier: Programming Language :: Python :: 3
Classifier: Programming Language :: Python :: 3.8
Classifier: Programming Language :: Python :: 3.9
Classifier: Programming Language :: Python :: 3.10
Classifier: Programming Language :: Python :: 3.11
Requires-Python: >=3.8
License-File: LICENSE
Requires-Dist: numpy>=1.19.0
Requires-Dist: matplotlib>=3.3.0
Requires-Dist: scipy>=1.6.0
Requires-Dist: networkx>=2.5
Requires-Dist: scikit-learn>=0.24.0
Provides-Extra: dev
Requires-Dist: pytest>=6.0; extra == "dev"
Requires-Dist: pytest-cov; extra == "dev"
Requires-Dist: black; extra == "dev"
Requires-Dist: flake8; extra == "dev"
Requires-Dist: mypy; extra == "dev"
Requires-Dist: sphinx; extra == "dev"
Requires-Dist: sphinx-rtd-theme; extra == "dev"
Dynamic: author
Dynamic: home-page
Dynamic: license-file
Dynamic: requires-python
